refinire_rag/__init__.py
refinire_rag/config.py
refinire_rag/corpusstore.py
refinire_rag/document_processor.py
refinire_rag/env_template.py
refinire_rag/exceptions.py
refinire_rag/utils.py
refinire_rag/application/__init__.py
refinire_rag/application/corpus_manager_new.py
refinire_rag/application/orchestrator_agent.py
refinire_rag/application/quality_lab.py
refinire_rag/application/query_engine_new.py
refinire_rag/chunking/__init__.py
refinire_rag/chunking/chunker.py
refinire_rag/chunking/sentence_chunker.py
refinire_rag/chunking/token_chunker.py
refinire_rag/corpus_store/sqlite_corpus_store.py
refinire_rag/embedding/__init__.py
refinire_rag/embedding/base.py
refinire_rag/embedding/openai_embedder.py
refinire_rag/embedding/tfidf_embedder.py
refinire_rag/evaluation/__init__.py
refinire_rag/evaluation/base_evaluator.py
refinire_rag/evaluation/bleu_evaluator.py
refinire_rag/evaluation/llm_judge_evaluator.py
refinire_rag/evaluation/questeval_evaluator.py
refinire_rag/evaluation/rouge_evaluator.py
refinire_rag/factories/__init__.py
refinire_rag/factories/plugin_factory.py
refinire_rag/keywordstore/__init__.py
refinire_rag/keywordstore/keyword_store.py
refinire_rag/keywordstore/tfidf_keyword_store.py
refinire_rag/loader/__init__.py
refinire_rag/loader/csv_loader.py
refinire_rag/loader/directory_loader.py
refinire_rag/loader/document_store_loader.py
refinire_rag/loader/file_tracker.py
refinire_rag/loader/html_loader.py
refinire_rag/loader/incremental_directory_loader.py
refinire_rag/loader/json_loader.py
refinire_rag/loader/loader.py
refinire_rag/loader/text_loader.py
refinire_rag/loader/filters/__init__.py
refinire_rag/loader/filters/base_filter.py
refinire_rag/loader/filters/date_filter.py
refinire_rag/loader/filters/extension_filter.py
refinire_rag/loader/filters/path_filter.py
refinire_rag/loader/filters/size_filter.py
refinire_rag/loader/models/__init__.py
refinire_rag/loader/models/change_set.py
refinire_rag/loader/models/file_info.py
refinire_rag-0.1.5.dist-info/METADATA
refinire_rag-0.1.5.dist-info/WHEEL
refinire_rag-0.1.5.dist-info/entry_points.txt
refinire_rag-0.1.5.dist-info/top_level.txt
refinire_rag-0.1.5.dist-info/RECORD
