Metadata-Version: 2.4
Name: refinire-rag
Version: 0.1.5
Summary: Add your description here
Requires-Python: >=3.10
Requires-Dist: numpy>=1.20.0
Requires-Dist: scikit-learn>=1.0.0
Requires-Dist: nltk>=3.8
Requires-Dist: refinire
Requires-Dist: oneenv
Provides-Extra: openai
Requires-Dist: openai>=1.0.0; extra == "openai"
Requires-Dist: tiktoken>=0.4.0; extra == "openai"
Provides-Extra: bm25
Requires-Dist: refinire-rag-bm25s-j>=0.0.3; extra == "bm25"
Provides-Extra: chroma
Requires-Dist: refinire-rag-chroma>=0.0.3; extra == "chroma"
Provides-Extra: dev
Requires-Dist: pytest>=8.0.0; extra == "dev"
Requires-Dist: pytest-cov>=4.1.0; extra == "dev"
Requires-Dist: black>=23.0.0; extra == "dev"
Requires-Dist: ruff>=0.1.0; extra == "dev"
